shellsteward/ShellSteward_ai.py
shellsteward/__init__.py
shellsteward/cli.py
shellsteward/data/commands.json
shellsteward-0.2.0.dist-info/licenses/LICENSE
shellsteward-0.2.0.dist-info/METADATA
shellsteward-0.2.0.dist-info/WHEEL
shellsteward-0.2.0.dist-info/entry_points.txt
shellsteward-0.2.0.dist-info/top_level.txt
shellsteward-0.2.0.dist-info/RECORD
